[
  {
    "profile": "dev",
    "rooms": ["local", "local-2", "bubu-home", "bubu-xrlab", "test", "dev", "xrlab-old"]
  },
  {
    "profile": "demo",
    "rooms": ["local", "xrlab-demo", "production"]
  },
  {
    "profile": "xrlab-meeting",
    "rooms": ["local", "xrlab-meeting"]
  },
  {
    "profile": "test",
    "rooms": ["local", "test"]
  },
  {
    "profile": "qa",
    "rooms": ["local", "dev", "production", "external"]
  },
  {
    "profile": "guest",
    "rooms": ["local", "external"]
  },
  {
    "profile": "uma",
    "rooms": ["local", "6gsandbox"]
  },
  {
    "profile": "kepler",
    "rooms": ["local", "juanXXIII", "juanXXIII-dev"]
  }
]
