[
  {
    "profile": "dev",
    "rooms": ["local", "local_2", "bubu_home", "bubu_xrlab", "test", "dev", "calabazon", "calabazon_2"]
  },
  {
    "profile": "demo",
    "rooms": ["local", "xrlab_demo", "production"]
  },
  {
    "profile": "test",
    "rooms": ["local", "production"]
  },
  {
    "profile": "uma",
    "rooms": ["local", "6gsandbox"]
  },
  {
    "profile": "kepler",
    "rooms": ["local", "juanXXIII"]
  },
  {
    "profile": "eucnc1",
    "rooms": ["local", "eucnc_1", "6gsandbox_1", "madrid_1", "malaga_1"]
  },
  {
    "profile": "eucnc2",
    "rooms": ["local", "xrlab", "terrace"]
  },
  {
    "profile": "poznan",
    "rooms": ["local", "eucnc_3", "6gsandbox_3"]
  },
  {
    "profile": "5GForum",
    "rooms": ["centro", "columna", "Madrid"]
  }
]
